setup.py
deep_learning_lab.egg-info/PKG-INFO
deep_learning_lab.egg-info/SOURCES.txt
deep_learning_lab.egg-info/dependency_links.txt
deep_learning_lab.egg-info/top_level.txt
dl_lab/__init__.py
dl_lab/pack.py