Metadata-Version: 2.1
Name: deep-learning-lab
Version: 1.0.0
Summary: This package can be used to get code for deep learning
Home-page: https://example.com
Author: anonymous
Author-email: your.email@example.com
License: MIT
Keywords: deep learning
Classifier: Development Status :: 3 - Alpha
Classifier: Intended Audience :: Developers
Classifier: Topic :: Software Development :: Build Tools
Classifier: License :: OSI Approved :: MIT License
Classifier: Programming Language :: Python :: 3.8
Classifier: Programming Language :: Python :: 3.9
Classifier: Programming Language :: Python :: 3.10
Classifier: Programming Language :: Python :: 3.11
